pyhub/__init__.py
pyhub/mcptools/__init__.py
pyhub/mcptools/__main__.py
pyhub/mcptools/urls.py
pyhub/mcptools/apple/__init__.py
pyhub/mcptools/apple/__main__.py
pyhub/mcptools/apple/contacts.py
pyhub/mcptools/apple/mail.py
pyhub/mcptools/apple/messages.py
pyhub/mcptools/apple/notes.py
pyhub/mcptools/apple/tools.py
pyhub/mcptools/apple/utils.py
pyhub/mcptools/browser/__init__.py
pyhub/mcptools/browser/__main__.py
pyhub/mcptools/browser/apps.py
pyhub/mcptools/browser/tools.py
pyhub/mcptools/core/__init__.py
pyhub/mcptools/core/apps.py
pyhub/mcptools/core/asgi.py
pyhub/mcptools/core/choices.py
pyhub/mcptools/core/cli.py
pyhub/mcptools/core/docker.py
pyhub/mcptools/core/email_types.py
pyhub/mcptools/core/email_utils.py
pyhub/mcptools/core/exceptions.py
pyhub/mcptools/core/fastmcp.py
pyhub/mcptools/core/fields.py
pyhub/mcptools/core/init.py
pyhub/mcptools/core/json_utils.py
pyhub/mcptools/core/routers.py
pyhub/mcptools/core/settings.py
pyhub/mcptools/core/sidecar.py
pyhub/mcptools/core/terminal.py
pyhub/mcptools/core/types.py
pyhub/mcptools/core/updater.py
pyhub/mcptools/core/versions.py
pyhub/mcptools/core/templatetags/applescript_tags.py
pyhub/mcptools/core/utils/__init__.py
pyhub/mcptools/core/utils/process.py
pyhub/mcptools/core/utils/sse.py
pyhub/mcptools/fs/__init__.py
pyhub/mcptools/fs/__main__.py
pyhub/mcptools/fs/tools.py
pyhub/mcptools/fs/utils.py
pyhub/mcptools/images/__init__.py
pyhub/mcptools/images/__main__.py
pyhub/mcptools/images/apps.py
pyhub/mcptools/images/generators.py
pyhub/mcptools/images/tools.py
pyhub/mcptools/images/types.py
pyhub/mcptools/images/utils.py
pyhub/mcptools/maps/__init__.py
pyhub/mcptools/maps/__main__.py
pyhub/mcptools/maps/types.py
pyhub/mcptools/maps/tools/__init__.py
pyhub/mcptools/maps/tools/naver.py
pyhub/mcptools/microsoft/__init__.py
pyhub/mcptools/microsoft/__main__.py
pyhub/mcptools/microsoft/tools.py
pyhub/mcptools/microsoft/excel/__init__.py
pyhub/mcptools/microsoft/excel/__main__.py
pyhub_mcptools-0.9.8.dist-info/METADATA
pyhub_mcptools-0.9.8.dist-info/WHEEL
pyhub_mcptools-0.9.8.dist-info/entry_points.txt
pyhub_mcptools-0.9.8.dist-info/RECORD
