Metadata-Version: 2.4
Name: pyhub-mcptools
Version: 0.9.8
Summary: 파이썬사랑방 MCP 도구
Project-URL: Homepage, https://github.com/pyhub-kr/pyhub-mcptools
Project-URL: Documentation, https://pyhub-kr.github.io/pyhub-mcptools
Project-URL: Bug Tracker, https://github.com/pyhub-kr/pyhub-mcptools/issues
Project-URL: Source Code, https://github.com/pyhub-kr/pyhub-mcptools
Author-email: Chinseok Lee <me@pyhub.kr>
License: MIT
Classifier: Development Status :: 3 - Alpha
Classifier: Intended Audience :: Developers
Classifier: Intended Audience :: End Users/Desktop
Classifier: License :: OSI Approved :: MIT License
Classifier: Programming Language :: Python :: 3
Classifier: Programming Language :: Python :: 3.11
Classifier: Programming Language :: Python :: 3.12
Classifier: Programming Language :: Python :: 3.13
Classifier: Topic :: Office/Business
Classifier: Topic :: Office/Business :: Office Suites
Classifier: Topic :: Software Development :: Libraries :: Python Modules
Requires-Python: >=3.11
Requires-Dist: aiofiles
Requires-Dist: channels
Requires-Dist: channels-redis
Requires-Dist: cloudpickle
Requires-Dist: django-environ
Requires-Dist: django>=5.2
Requires-Dist: html2text
Requires-Dist: httpx
Requires-Dist: mcp
Requires-Dist: mcp-proxy
Requires-Dist: platformdirs
Requires-Dist: psutil
Requires-Dist: pywin32; sys_platform == 'win32'
Requires-Dist: typer
Requires-Dist: tzlocal
Requires-Dist: uvicorn
Provides-Extra: all
Requires-Dist: bs4; extra == 'all'
Requires-Dist: matplotlib; extra == 'all'
Requires-Dist: numpy; extra == 'all'
Requires-Dist: pandas; extra == 'all'
Requires-Dist: pillow; extra == 'all'
Requires-Dist: playwright; extra == 'all'
Requires-Dist: restrictedpython; extra == 'all'
Requires-Dist: seaborn; extra == 'all'
Requires-Dist: vadersentiment; extra == 'all'
Requires-Dist: xlwings; extra == 'all'
Provides-Extra: browser
Requires-Dist: bs4; extra == 'browser'
Requires-Dist: playwright; extra == 'browser'
Provides-Extra: build
Requires-Dist: build; extra == 'build'
Requires-Dist: setuptools; extra == 'build'
Requires-Dist: twine; extra == 'build'
Requires-Dist: wheel; extra == 'build'
Provides-Extra: dev
Requires-Dist: black; extra == 'dev'
Requires-Dist: djlint; extra == 'dev'
Requires-Dist: isort; extra == 'dev'
Requires-Dist: mypy; extra == 'dev'
Requires-Dist: pytest; extra == 'dev'
Requires-Dist: pytest-asyncio; extra == 'dev'
Requires-Dist: pytest-cov; extra == 'dev'
Requires-Dist: pytest-httpx; extra == 'dev'
Requires-Dist: ruff; extra == 'dev'
Provides-Extra: docs
Requires-Dist: mkdocs-git-revision-date-localized-plugin; extra == 'docs'
Requires-Dist: mkdocs-glightbox; extra == 'docs'
Requires-Dist: mkdocs-material>=9.1.0; extra == 'docs'
Requires-Dist: mkdocs-material[imaging]; extra == 'docs'
Requires-Dist: mkdocs>=1.4.0; extra == 'docs'
Requires-Dist: mkdocstrings-python>=1.0.0; extra == 'docs'
Requires-Dist: mkdocstrings>=0.20.0; extra == 'docs'
Provides-Extra: excel
Requires-Dist: xlwings; extra == 'excel'
Provides-Extra: images
Requires-Dist: pillow; extra == 'images'
Provides-Extra: music
Requires-Dist: bs4; extra == 'music'
Provides-Extra: python
Requires-Dist: matplotlib; extra == 'python'
Requires-Dist: numpy; extra == 'python'
Requires-Dist: pandas; extra == 'python'
Requires-Dist: restrictedpython; extra == 'python'
Requires-Dist: seaborn; extra == 'python'
Provides-Extra: sentiment
Requires-Dist: vadersentiment; extra == 'sentiment'
